anyconfig_cbor2_backend/__init__.py
anyconfig_cbor2_backend/cbor2_.py
anyconfig_cbor2_backend-0.2.0.dist-info/LICENSE.MIT
anyconfig_cbor2_backend-0.2.0.dist-info/METADATA
anyconfig_cbor2_backend-0.2.0.dist-info/WHEEL
anyconfig_cbor2_backend-0.2.0.dist-info/entry_points.txt
anyconfig_cbor2_backend-0.2.0.dist-info/top_level.txt
anyconfig_cbor2_backend-0.2.0.dist-info/RECORD
